enzymefinance/abis/__init__.py
enzymefinance/abis/abis.py
enzymefinance/abis/abis/IAaveDebtPositionLib.abi.json
enzymefinance/abis/abis/IAaveDebtPositionParser.abi.json
enzymefinance/abis/abis/IAaveV2ATokenListOwner.abi.json
enzymefinance/abis/abis/IAaveV2Adapter.abi.json
enzymefinance/abis/abis/IAaveV3ATokenListOwner.abi.json
enzymefinance/abis/abis/IAaveV3Adapter.abi.json
enzymefinance/abis/abis/IAaveV3DebtPositionLib.abi.json
enzymefinance/abis/abis/IAaveV3DebtPositionParser.abi.json
enzymefinance/abis/abis/IAaveV3FlashLoanAssetManager.abi.json
enzymefinance/abis/abis/IAddressListRegistry.abi.json
enzymefinance/abis/abis/IAllowedAdapterIncomingAssetsPolicy.abi.json
enzymefinance/abis/abis/IAllowedAdaptersPerManagerPolicy.abi.json
enzymefinance/abis/abis/IAllowedAdaptersPolicy.abi.json
enzymefinance/abis/abis/IAllowedAssetsForRedemptionPolicy.abi.json
enzymefinance/abis/abis/IAllowedDepositRecipientsPolicy.abi.json
enzymefinance/abis/abis/IAllowedExternalPositionTypesPerManagerPolicy.abi.json
enzymefinance/abis/abis/IAllowedExternalPositionTypesPolicy.abi.json
enzymefinance/abis/abis/IAllowedRedeemersForSpecificAssetsPolicy.abi.json
enzymefinance/abis/abis/IAllowedSharesTransferRecipientsPolicy.abi.json
enzymefinance/abis/abis/IArbitraryLoanPositionLib.abi.json
enzymefinance/abis/abis/IArbitraryLoanPositionParser.abi.json
enzymefinance/abis/abis/IArbitraryLoanTotalNominalDeltaOracleModule.abi.json
enzymefinance/abis/abis/IArbitraryTokenPhasedSharesWrapperFactory.abi.json
enzymefinance/abis/abis/IArbitraryTokenPhasedSharesWrapperLib.abi.json
enzymefinance/abis/abis/IArbitraryTokenPhasedSharesWrapperProxy.abi.json
enzymefinance/abis/abis/IArbitraryValueOracle.abi.json
enzymefinance/abis/abis/IArrakisV2Adapter.abi.json
enzymefinance/abis/abis/IArrakisV2PriceFeed.abi.json
enzymefinance/abis/abis/IAssetValueCalculator.abi.json
enzymefinance/abis/abis/IAuraBalancerV2LpStakingAdapter.abi.json
enzymefinance/abis/abis/IAuraBalancerV2LpStakingWrapperFactory.abi.json
enzymefinance-0.1.1.dist-info/LICENSE
enzymefinance-0.1.1.dist-info/METADATA
enzymefinance-0.1.1.dist-info/WHEEL
enzymefinance-0.1.1.dist-info/top_level.txt
enzymefinance-0.1.1.dist-info/RECORD
