Metadata-Version: 2.2
Name: enzymefinance
Version: 0.1.1
Summary: Official Python SDK for the Enzyme Protocol
Author-email: Enzyme <info@enzyme.finance>
License: MIT License
Project-URL: Homepage, https://github.com/enzymefinance/sdk-python
Project-URL: Documentation, https://sdk.enzyme.finance
Project-URL: Repository, https://github.com/enzymefinance/sdk-python
Classifier: Development Status :: 3 - Alpha
Classifier: Intended Audience :: Developers
Classifier: License :: OSI Approved :: MIT License
Classifier: Operating System :: OS Independent
Classifier: Programming Language :: Python :: 3
Classifier: Programming Language :: Python :: 3.10
Classifier: Programming Language :: Python :: 3.11
Classifier: Programming Language :: Python :: 3.12
Classifier: Programming Language :: Python :: 3.13
Classifier: Programming Language :: Python :: 3.14
Requires-Python: >=3.9
License-File: LICENSE
Requires-Dist: web3>=7.8.0
Requires-Dist: requests>=2.32.0
